rdfformat/__init__.py
rdfformat/rdf_generator.py
rdfformat/generator/__init__.py
rdfformat/generator/constants.py
rdfformat/generator/rdf_helper.py
rdfformat/generator/rdf_manager.py
rdfformat/generator/rdf_ont_init.py
rdfformat/generator/rdflib_carson_types_handler.py
rdfformat/generator/rdflib_facilities_handler.py
rdfformat/generator/rdflib_function_handler.py
rdfformat/generator/rdflib_generaltypes_handler.py
rdfformat/generator/rdflib_states_handler.py
rdfformat/generator/rdflib_subfields_handler.py
rdfformat/generator/rdflib_units_handler.py
rdfformat/generator/yaml_handler.py
rdfformat/tests/__init__.py
rdfformat/tests/rdf_helper_test.py
rdfformat/tests/rdf_manager_test.py
rdfformat/tests/rdf_ont_init_test.py
rdfformat/tests/rdflib_carson_types_handler_test.py
rdfformat/tests/rdflib_facilities_handler_test.py
rdfformat/tests/rdflib_function_handler_test.py
rdfformat/tests/rdflib_generaltypes_handler_test.py
rdfformat/tests/rdflib_states_handler_test.py
rdfformat/tests/rdflib_subfields_handler_test.py
rdfformat/tests/rdflib_units_handler_test.py
ideology_rdf_generator-0.0.1.dist-info/LICENSE.txt
ideology_rdf_generator-0.0.1.dist-info/METADATA
ideology_rdf_generator-0.0.1.dist-info/WHEEL
ideology_rdf_generator-0.0.1.dist-info/top_level.txt
ideology_rdf_generator-0.0.1.dist-info/RECORD
